{"version":2,"kind":"Notebook","sha256":"c421053b7f425005c06ad81a000476773c62961d869dde4abd2139593908bbd6","slug":"notebooks.complex-search","location":"/notebooks/complex-search.ipynb","dependencies":[],"frontmatter":{"title":"Complex Searching with intake-esgf","content_includes_title":true,"kernelspec":{"name":"python3","display_name":"Python 3 (ipykernel)","language":"python"},"authors":[{"nameParsed":{"literal":"Project Pythia Community","given":"Project Pythia","family":"Community"},"name":"Project Pythia Community","url":"https://projectpythia.org/","id":"contributors-myst-generated-uid-0"}],"open_access":true,"license":{"content":{"id":"Apache-2.0","url":"https://opensource.org/licenses/Apache-2.0","name":"Apache License 2.0","free":true,"osi":true},"code":{"id":"CC-BY-4.0","url":"https://creativecommons.org/licenses/by/4.0/","name":"Creative Commons Attribution 4.0 International","free":true,"CC":true}},"github":"https://github.com/projectpythia/esgf-cookbook","copyright":"2023","numbering":{"title":{"offset":1}},"edit_url":"https://github.com/projectpythia/esgf-cookbook/blob/HEAD/notebooks/complex-search.ipynb","thumbnail":"/esgf-cookbook/build/esgf2-us-c5fdca775b6f5524ccffcb4b0195ba2c.png","exports":[{"format":"ipynb","filename":"complex-search.ipynb","url":"/esgf-cookbook/build/complex-search-c7a939d6f84547b9139dc8e8192b234b.ipynb"}]},"widgets":{},"mdast":{"type":"root","children":[{"type":"block","kind":"notebook-content","children":[{"type":"paragraph","position":{"start":{"line":1,"column":1},"end":{"line":1,"column":1}},"children":[{"type":"image","url":"/esgf-cookbook/build/esgf2-us-c5fdca775b6f5524ccffcb4b0195ba2c.png","alt":"ESGF logo","key":"BRrTNC2tXH","urlSource":"images/logos/esgf2-us.png"}],"key":"QA6Xtfq5Ug"}],"key":"cvcIPWDW0u"},{"type":"block","kind":"notebook-content","children":[{"type":"heading","depth":1,"position":{"start":{"line":1,"column":1},"end":{"line":1,"column":1}},"children":[{"type":"text","value":"Complex Searching with ","position":{"start":{"line":1,"column":1},"end":{"line":1,"column":1}},"key":"jQpAgV0ubu"},{"type":"inlineCode","value":"intake-esgf","position":{"start":{"line":1,"column":1},"end":{"line":1,"column":1}},"key":"refwuiNPUq"}],"identifier":"complex-searching-with-intake-esgf","label":"Complex Searching with intake-esgf","html_id":"complex-searching-with-intake-esgf","implicit":true,"key":"wBIXvbeokZ"},{"type":"heading","depth":2,"position":{"start":{"line":3,"column":1},"end":{"line":3,"column":1}},"children":[{"type":"text","value":"Overview","position":{"start":{"line":3,"column":1},"end":{"line":3,"column":1}},"key":"XtdirV0D6l"}],"identifier":"overview","label":"Overview","html_id":"overview","implicit":true,"key":"klrkT2igTN"},{"type":"paragraph","position":{"start":{"line":5,"column":1},"end":{"line":5,"column":1}},"children":[{"type":"text","value":"In this tutorial we will present an interface under design to facilitate complex searching using ","position":{"start":{"line":5,"column":1},"end":{"line":5,"column":1}},"key":"m0qUW8lh7r"},{"type":"link","url":"https://github.com/esgf2-us/intake-esgf","position":{"start":{"line":5,"column":1},"end":{"line":5,"column":1}},"children":[{"type":"text","value":"intake-esgf","position":{"start":{"line":5,"column":1},"end":{"line":5,"column":1}},"key":"IgmEqvqopp"}],"urlSource":"https://github.com/esgf2-us/intake-esgf","error":true,"key":"idz5jQnyyG"},{"type":"text","value":". ","position":{"start":{"line":5,"column":1},"end":{"line":5,"column":1}},"key":"ZxrAECc7E0"},{"type":"inlineCode","value":"intake-esgf","position":{"start":{"line":5,"column":1},"end":{"line":5,"column":1}},"key":"d4auxmYPHH"},{"type":"text","value":" is a small ","position":{"start":{"line":5,"column":1},"end":{"line":5,"column":1}},"key":"KnPRb0uuYq"},{"type":"inlineCode","value":"intake","position":{"start":{"line":5,"column":1},"end":{"line":5,"column":1}},"key":"XErRI1LtLh"},{"type":"text","value":" and ","position":{"start":{"line":5,"column":1},"end":{"line":5,"column":1}},"key":"nUx6XcmNjw"},{"type":"inlineCode","value":"intake-esm","position":{"start":{"line":5,"column":1},"end":{"line":5,"column":1}},"key":"NwreyyBGe5"},{"type":"text","value":" ","position":{"start":{"line":5,"column":1},"end":{"line":5,"column":1}},"key":"yfrxsIlgOx"},{"type":"emphasis","position":{"start":{"line":5,"column":1},"end":{"line":5,"column":1}},"children":[{"type":"text","value":"inspired","position":{"start":{"line":5,"column":1},"end":{"line":5,"column":1}},"key":"ug9Raovrqy"}],"key":"hzLFjT7ats"},{"type":"text","value":" package under development in ESGF2. Please note that there is a name collison with an existing package in PyPI and conda. You will need to install the package from ","position":{"start":{"line":5,"column":1},"end":{"line":5,"column":1}},"key":"Sxp0rGtXvr"},{"type":"link","url":"https://github.com/esgf2-us/intake-esgf","position":{"start":{"line":5,"column":1},"end":{"line":5,"column":1}},"children":[{"type":"text","value":"source","position":{"start":{"line":5,"column":1},"end":{"line":5,"column":1}},"key":"xGuTzqEPvn"}],"urlSource":"https://github.com/esgf2-us/intake-esgf","error":true,"key":"qc2I3I3CaD"},{"type":"text","value":".","position":{"start":{"line":5,"column":1},"end":{"line":5,"column":1}},"key":"hJK0GDiLLA"}],"key":"zPXaRKgmXQ"},{"type":"heading","depth":2,"position":{"start":{"line":7,"column":1},"end":{"line":7,"column":1}},"children":[{"type":"text","value":"Prerequisites","position":{"start":{"line":7,"column":1},"end":{"line":7,"column":1}},"key":"FwhfYRNjzm"}],"identifier":"prerequisites","label":"Prerequisites","html_id":"prerequisites","implicit":true,"key":"K2N3aJrb0D"},{"type":"table","position":{"start":{"line":9,"column":1},"end":{"line":14,"column":1}},"children":[{"type":"tableRow","position":{"start":{"line":9,"column":1},"end":{"line":9,"column":1}},"children":[{"type":"tableCell","header":true,"position":{"start":{"line":9,"column":1},"end":{"line":9,"column":1}},"children":[{"type":"text","value":"Concepts","position":{"start":{"line":9,"column":1},"end":{"line":9,"column":1}},"key":"XWRGf5xKZ5"}],"key":"BEVVKhSVNH"},{"type":"tableCell","header":true,"position":{"start":{"line":9,"column":1},"end":{"line":9,"column":1}},"children":[{"type":"text","value":"Importance","position":{"start":{"line":9,"column":1},"end":{"line":9,"column":1}},"key":"Pf7FIgmunA"}],"key":"x04WmSeNOP"},{"type":"tableCell","header":true,"position":{"start":{"line":9,"column":1},"end":{"line":9,"column":1}},"children":[{"type":"text","value":"Notes","position":{"start":{"line":9,"column":1},"end":{"line":9,"column":1}},"key":"ceeuMjzfxO"}],"key":"RuNv8QRBKz"}],"key":"D4MsSvVyIP"},{"type":"tableRow","position":{"start":{"line":11,"column":1},"end":{"line":11,"column":1}},"children":[{"type":"tableCell","position":{"start":{"line":11,"column":1},"end":{"line":11,"column":1}},"children":[{"type":"link","url":"https://github.com/esgf2-us/intake-esgf","position":{"start":{"line":11,"column":1},"end":{"line":11,"column":1}},"children":[{"type":"text","value":"Install Package","position":{"start":{"line":11,"column":1},"end":{"line":11,"column":1}},"key":"LboDMoMn9S"}],"urlSource":"https://github.com/esgf2-us/intake-esgf","error":true,"key":"zGLcgnJxin"}],"key":"cUvJWOhpBZ"},{"type":"tableCell","position":{"start":{"line":11,"column":1},"end":{"line":11,"column":1}},"children":[{"type":"text","value":"Necessary","position":{"start":{"line":11,"column":1},"end":{"line":11,"column":1}},"key":"zOEYKpdflq"}],"key":"mFFeigYTbl"},{"type":"tableCell","position":{"start":{"line":11,"column":1},"end":{"line":11,"column":1}},"children":[],"key":"EV7qjc5AxD"}],"key":"q0mInsxJk3"},{"type":"tableRow","position":{"start":{"line":12,"column":1},"end":{"line":12,"column":1}},"children":[{"type":"tableCell","position":{"start":{"line":12,"column":1},"end":{"line":12,"column":1}},"children":[{"type":"link","url":"https://foundations.projectpythia.org/core/data-formats/netcdf-cf.html","position":{"start":{"line":12,"column":1},"end":{"line":12,"column":1}},"children":[{"type":"text","value":"Understanding of NetCDF","position":{"start":{"line":12,"column":1},"end":{"line":12,"column":1}},"key":"p935dMEimG"}],"urlSource":"https://foundations.projectpythia.org/core/data-formats/netcdf-cf.html","key":"KcMZ2PGHgi"}],"key":"svwSx6NueW"},{"type":"tableCell","position":{"start":{"line":12,"column":1},"end":{"line":12,"column":1}},"children":[{"type":"text","value":"Helpful","position":{"start":{"line":12,"column":1},"end":{"line":12,"column":1}},"key":"VRDFvTeJxC"}],"key":"EccvR9bnln"},{"type":"tableCell","position":{"start":{"line":12,"column":1},"end":{"line":12,"column":1}},"children":[{"type":"text","value":"Familiarity with metadata structure","position":{"start":{"line":12,"column":1},"end":{"line":12,"column":1}},"key":"AbjpvuOihr"}],"key":"hm46po1hre"}],"key":"JKPuzcu6vq"},{"type":"tableRow","position":{"start":{"line":13,"column":1},"end":{"line":13,"column":1}},"children":[{"type":"tableCell","position":{"start":{"line":13,"column":1},"end":{"line":13,"column":1}},"children":[{"type":"text","value":"Familiar with ","position":{"start":{"line":13,"column":1},"end":{"line":13,"column":1}},"key":"aYM0vuOZpG"},{"type":"link","url":"https://intake-esm.readthedocs.io/en/stable/","position":{"start":{"line":13,"column":1},"end":{"line":13,"column":1}},"children":[{"type":"text","value":"intake-esm","position":{"start":{"line":13,"column":1},"end":{"line":13,"column":1}},"key":"GRjSbnJOYo"}],"urlSource":"https://intake-esm.readthedocs.io/en/stable/","key":"AZJNxmF6Cp"}],"key":"yQJAqpYiB9"},{"type":"tableCell","position":{"start":{"line":13,"column":1},"end":{"line":13,"column":1}},"children":[{"type":"text","value":"Helpful","position":{"start":{"line":13,"column":1},"end":{"line":13,"column":1}},"key":"xx6H7XHtNK"}],"key":"FHkafuVIAL"},{"type":"tableCell","position":{"start":{"line":13,"column":1},"end":{"line":13,"column":1}},"children":[{"type":"text","value":"Similar interface","position":{"start":{"line":13,"column":1},"end":{"line":13,"column":1}},"key":"V2NNDbEDDH"}],"key":"fWyaJxCFUT"}],"key":"ui90KefkCt"},{"type":"tableRow","position":{"start":{"line":14,"column":1},"end":{"line":14,"column":1}},"children":[{"type":"tableCell","position":{"start":{"line":14,"column":1},"end":{"line":14,"column":1}},"children":[{"type":"cite","url":"https://doi.org/10.1029/2008JD010405","position":{"start":{"line":14,"column":1},"end":{"line":14,"column":1}},"children":[{"type":"text","value":"Transient climate response","position":{"start":{"line":14,"column":1},"end":{"line":14,"column":1}},"key":"TRPqhLF9AB"}],"kind":"narrative","label":"Gregory_2008","identifier":"https://doi.org/10.1029/2008JD010405","enumerator":"1","key":"K7S66vjKFV"}],"key":"EokDPNRNhf"},{"type":"tableCell","position":{"start":{"line":14,"column":1},"end":{"line":14,"column":1}},"children":[{"type":"text","value":"Background","position":{"start":{"line":14,"column":1},"end":{"line":14,"column":1}},"key":"d6IOpzxiZx"}],"key":"x3BrXwUnFq"},{"type":"tableCell","position":{"start":{"line":14,"column":1},"end":{"line":14,"column":1}},"children":[],"key":"ulYUYVhW41"}],"key":"If2ysc45fi"}],"key":"uUNBf7oEZV"},{"type":"list","ordered":false,"spread":false,"position":{"start":{"line":15,"column":1},"end":{"line":16,"column":1}},"children":[{"type":"listItem","spread":true,"position":{"start":{"line":15,"column":1},"end":{"line":16,"column":1}},"children":[{"type":"strong","position":{"start":{"line":15,"column":1},"end":{"line":15,"column":1}},"children":[{"type":"text","value":"Time to learn","position":{"start":{"line":15,"column":1},"end":{"line":15,"column":1}},"key":"cwlRRv3Wrk"}],"key":"zVMDyFQLLj"},{"type":"text","value":": 30 minutes","position":{"start":{"line":15,"column":1},"end":{"line":15,"column":1}},"key":"CPEUCYZ1gQ"}],"key":"InWWNfTEcD"}],"key":"wcclJBYhot"},{"type":"heading","depth":2,"position":{"start":{"line":17,"column":1},"end":{"line":17,"column":1}},"children":[{"type":"text","value":"Imports","position":{"start":{"line":17,"column":1},"end":{"line":17,"column":1}},"key":"UvarWlBsdZ"}],"identifier":"imports","label":"Imports","html_id":"imports","implicit":true,"key":"KxLngWYqHW"}],"key":"JWsKuKLzjf"},{"type":"block","kind":"notebook-code","children":[{"type":"code","lang":"python","executable":true,"value":"import intake_esgf\nfrom intake_esgf import ESGFCatalog","key":"OVO7sMNRA3"},{"type":"output","id":"qDA9s0A5MrGR8Z-Ca41Lq","data":[],"key":"n0smiAF2jg"}],"key":"sW4Mcgr6sd"},{"type":"block","kind":"notebook-content","children":[{"type":"heading","depth":2,"position":{"start":{"line":1,"column":1},"end":{"line":1,"column":1}},"children":[{"type":"text","value":"Initializing the Catalog","position":{"start":{"line":1,"column":1},"end":{"line":1,"column":1}},"key":"VwVEcNx8Ef"}],"identifier":"initializing-the-catalog","label":"Initializing the Catalog","html_id":"initializing-the-catalog","implicit":true,"key":"b00eY5iPEj"},{"type":"paragraph","position":{"start":{"line":3,"column":1},"end":{"line":3,"column":1}},"children":[{"type":"text","value":"As with ","position":{"start":{"line":3,"column":1},"end":{"line":3,"column":1}},"key":"K2iCmv5L2B"},{"type":"inlineCode","value":"intake-esm","position":{"start":{"line":3,"column":1},"end":{"line":3,"column":1}},"key":"AwMqp9Mlob"},{"type":"text","value":" we first instantiate the catalog. However, since we will populate the catalog with search results, the catalog starts empty. Internally, we query different ESGF index nodes for information about what datasets you wish to include in your analysis. As ESGF2 is actively working on an index redesign, our catlogs by default point to a Globus (ElasticSearch) based index at ALCF (Argonne Leadership Computing Facility).","position":{"start":{"line":3,"column":1},"end":{"line":3,"column":1}},"key":"zAJvTwsALj"}],"key":"Nmr6ptdMzb"}],"key":"U9d6lAB9QH"},{"type":"block","kind":"notebook-code","children":[{"type":"code","lang":"python","executable":true,"value":"cat = ESGFCatalog()\nprint(cat)\nfor ind in cat.indices: # Which indices are included?\n    print(ind)","key":"VCs4k9HtS6"},{"type":"output","id":"UaiyA9LWnV491xHtoIWe1","data":[{"output_type":"stream","name":"stdout","text":"Perform a search() to populate the catalog.\nGlobusESGFIndex('anl-dev')\nGlobusESGFIndex('ornl-dev')\n"}],"key":"PxftpqYZtJ"}],"key":"CyAxSsTnti"},{"type":"block","kind":"notebook-content","children":[{"type":"paragraph","position":{"start":{"line":1,"column":1},"end":{"line":1,"column":1}},"children":[{"type":"text","value":"We also provide support for connecting to the ESGF1 Solr-based indices. You may specify a server in the dictionary or multiple servers - just make sure to include ","position":{"start":{"line":1,"column":1},"end":{"line":1,"column":1}},"key":"vLFI9kJvTh"},{"type":"inlineCode","value":"True","position":{"start":{"line":1,"column":1},"end":{"line":1,"column":1}},"key":"BP6DcgOrOs"},{"type":"text","value":".","position":{"start":{"line":1,"column":1},"end":{"line":1,"column":1}},"key":"HFYU3JiCzj"}],"key":"cbNrAnfEVh"},{"type":"paragraph","position":{"start":{"line":3,"column":1},"end":{"line":3,"column":1}},"children":[{"type":"text","value":"Uncommend the line setting ","position":{"start":{"line":3,"column":1},"end":{"line":3,"column":1}},"key":"ncQtBfPH47"},{"type":"inlineCode","value":"all_indices=True","position":{"start":{"line":3,"column":1},"end":{"line":3,"column":1}},"key":"ALn5RrxIFH"},{"type":"text","value":" to include all available indices.","position":{"start":{"line":3,"column":1},"end":{"line":3,"column":1}},"key":"F92uzBjib3"}],"key":"Am5B21x5NQ"}],"key":"PjaVUYgDVv"},{"type":"block","kind":"notebook-code","children":[{"type":"code","lang":"python","executable":true,"value":"intake_esgf.conf.set(indices={\"esgf-node.llnl.gov\": True,\n                              \"esgf-node.ornl.gov\": True,\n                              \"esgf.ceda.ac.uk\": True})\n\nintake_esgf.conf.set(all_indices=True)  # all federated indices\n\ncat = ESGFCatalog()\nfor ind in cat.indices:\n    print(ind)","key":"L1wZFthe3V"},{"type":"output","id":"FEXRXIEnm5ET28WwVgQeA","data":[{"output_type":"stream","name":"stdout","text":"GlobusESGFIndex('anl-dev')\nGlobusESGFIndex('ornl-dev')\nGlobusESGFIndex('ESGF2-US-1.5-Catalog')\nSolrESGFIndex('esgf.ceda.ac.uk')\nSolrESGFIndex('esgf-data.dkrz.de')\nSolrESGFIndex('esgf-node.ipsl.upmc.fr')\nSolrESGFIndex('esg-dn1.nsc.liu.se')\nSolrESGFIndex('esgf.nci.org.au')\nSolrESGFIndex('esgf-node.ornl.gov')\nSolrESGFIndex('esgf-node.llnl.gov')\n"}],"key":"YhUCKWi6ex"}],"key":"CJMDUNpb25"},{"type":"block","kind":"notebook-content","children":[{"type":"heading","depth":2,"position":{"start":{"line":1,"column":1},"end":{"line":1,"column":1}},"children":[{"type":"text","value":"Populate the catalog","position":{"start":{"line":1,"column":1},"end":{"line":1,"column":1}},"key":"msjgkANFZ2"}],"identifier":"populate-the-catalog","label":"Populate the catalog","html_id":"populate-the-catalog","implicit":true,"key":"tZ0cMctqws"},{"type":"paragraph","position":{"start":{"line":3,"column":1},"end":{"line":3,"column":1}},"children":[{"type":"text","value":"Many times, an analysis will require several variables across multiple experiments. For example, if one were to compute the transient climate response (TCRE), you would need tempererature (","position":{"start":{"line":3,"column":1},"end":{"line":3,"column":1}},"key":"haP14muOWd"},{"type":"inlineCode","value":"tas","position":{"start":{"line":3,"column":1},"end":{"line":3,"column":1}},"key":"LhP57kC3zH"},{"type":"text","value":") and carbon emissions from land (","position":{"start":{"line":3,"column":1},"end":{"line":3,"column":1}},"key":"pbVV0qkLxS"},{"type":"inlineCode","value":"nbp","position":{"start":{"line":3,"column":1},"end":{"line":3,"column":1}},"key":"hQSvbV0PCH"},{"type":"text","value":") and ocean (","position":{"start":{"line":3,"column":1},"end":{"line":3,"column":1}},"key":"hAjZZwWiW4"},{"type":"inlineCode","value":"fgco2","position":{"start":{"line":3,"column":1},"end":{"line":3,"column":1}},"key":"hNDXwB9W75"},{"type":"text","value":") for a 1% CO2 increase experiment (","position":{"start":{"line":3,"column":1},"end":{"line":3,"column":1}},"key":"S7detrNSO6"},{"type":"inlineCode","value":"1pctCO2","position":{"start":{"line":3,"column":1},"end":{"line":3,"column":1}},"key":"SElZIXCxb8"},{"type":"text","value":") as well as the control experiment (","position":{"start":{"line":3,"column":1},"end":{"line":3,"column":1}},"key":"We0nKC9kFU"},{"type":"inlineCode","value":"piControl","position":{"start":{"line":3,"column":1},"end":{"line":3,"column":1}},"key":"Sh3YV9kV8i"},{"type":"text","value":"). If TCRE is not in your particular science, that is ok for this notebook. It is a motivating example and the specifics are less important than the search concepts. First, we perform a search in a familiar syntax.","position":{"start":{"line":3,"column":1},"end":{"line":3,"column":1}},"key":"q4lghC9Pmc"}],"key":"EkwNPowvVL"}],"key":"hDKQKQV8PL"},{"type":"block","kind":"notebook-code","children":[{"type":"code","lang":"python","executable":true,"value":"cat.search(\n    experiment_id=[\"piControl\", \"1pctCO2\"],\n    variable_id=[\"tas\", \"fgco2\", \"nbp\"],\n    table_id=[\"Amon\", \"Omon\", \"Lmon\"],\n)\nprint(cat)","key":"KIihuTLyMb"},{"type":"output","id":"Yvj5VxiLd2czfbXfyjsxQ","data":[{"output_type":"display_data","metadata":{},"data":{"text/plain":{"content":"   Searching indices:   0%|          |0/10 [       ?index/s]","content_type":"text/plain"},"application/vnd.jupyter.widget-view+json":{"content":"{\"version_major\":2,\"version_minor\":0,\"model_id\":\"8900bc8bb067476291561be8310a529c\"}","content_type":"application/vnd.jupyter.widget-view+json"}}},{"output_type":"stream","name":"stderr","text":"/home/runner/micromamba/envs/esgf-cookbook-dev/lib/python3.11/site-packages/intake_esgf/catalog.py:316: UserWarning: SolrESGFIndex('esgf-node.ornl.gov') failed to return a response, results may be incomplete\n  warnings.warn(\n"},{"output_type":"stream","name":"stderr","text":"/home/runner/micromamba/envs/esgf-cookbook-dev/lib/python3.11/site-packages/intake_esgf/catalog.py:316: UserWarning: SolrESGFIndex('esgf-node.llnl.gov') failed to return a response, results may be incomplete\n  warnings.warn(\n"},{"output_type":"stream","name":"stdout","text":"Summary information for 424 results:\nmip_era                                                     [CMIP6]\nactivity_drs                                                 [CMIP]\ninstitution_id    [NCAR, MIROC, EC-Earth-Consortium, CCCma, CAS,...\nsource_id         [CESM2-WACCM-FV2, CESM2-FV2, MIROC-ES2H, EC-Ea...\nexperiment_id                                  [piControl, 1pctCO2]\nmember_id         [r1i2p2f1, r1i1p4f2, r1i1p1f1, r1i1p1f2, r2i1p...\ntable_id                                         [Lmon, Omon, Amon]\nvariable_id                                       [nbp, fgco2, tas]\ngrid_label                                            [gn, gr, gr1]\ndtype: object\n"}],"key":"r0FmHTploE"}],"key":"z6VZIDOe7E"},{"type":"block","kind":"notebook-content","children":[{"type":"paragraph","position":{"start":{"line":1,"column":1},"end":{"line":1,"column":1}},"children":[{"type":"text","value":"Internally, this launches simultaneous searches that are combined locally to provide a global view of what datasets are available. While the Solr indices themselves can be searched in distributed fashion, they will not report if an index has failed to return a response. As index nodes go down from time to time, this can leave you with a false impression that you have found all the datasets of interest. By managing the searches locally, ","position":{"start":{"line":1,"column":1},"end":{"line":1,"column":1}},"key":"pwIlTL62VX"},{"type":"inlineCode","value":"intake-esgf","position":{"start":{"line":1,"column":1},"end":{"line":1,"column":1}},"key":"qPLhlgTTYk"},{"type":"text","value":" can report back to you that an index has failed and that your results may be incomplete.","position":{"start":{"line":1,"column":1},"end":{"line":1,"column":1}},"key":"adwsp190ZI"}],"key":"doXi9JnVDq"},{"type":"paragraph","position":{"start":{"line":3,"column":1},"end":{"line":3,"column":1}},"children":[{"type":"text","value":"If you would like details about what ","position":{"start":{"line":3,"column":1},"end":{"line":3,"column":1}},"key":"YsWov8qpUo"},{"type":"inlineCode","value":"intake-esgf","position":{"start":{"line":3,"column":1},"end":{"line":3,"column":1}},"key":"EzPyZGFDBU"},{"type":"text","value":" is doing, look in the local cache directory (","position":{"start":{"line":3,"column":1},"end":{"line":3,"column":1}},"key":"qraGKM217x"},{"type":"inlineCode","value":"${HOME}/.esgf/","position":{"start":{"line":3,"column":1},"end":{"line":3,"column":1}},"key":"HM5jWiIuw9"},{"type":"text","value":") for a ","position":{"start":{"line":3,"column":1},"end":{"line":3,"column":1}},"key":"CRJLyHHA4t"},{"type":"inlineCode","value":"esgf.log","position":{"start":{"line":3,"column":1},"end":{"line":3,"column":1}},"key":"vr0qJgrS6U"},{"type":"text","value":" file. This is a full history of everything that ","position":{"start":{"line":3,"column":1},"end":{"line":3,"column":1}},"key":"MVPqnWiW3i"},{"type":"inlineCode","value":"intake-esgf","position":{"start":{"line":3,"column":1},"end":{"line":3,"column":1}},"key":"nzf2FFe1pu"},{"type":"text","value":" has searched, downloaded, or accessed. You can also look at just this session by calling ","position":{"start":{"line":3,"column":1},"end":{"line":3,"column":1}},"key":"LV0lCECL50"},{"type":"inlineCode","value":"session_log()","position":{"start":{"line":3,"column":1},"end":{"line":3,"column":1}},"key":"ahAeto7PKf"},{"type":"text","value":". In this case you will see how long each index took to return a response and if any failed","position":{"start":{"line":3,"column":1},"end":{"line":3,"column":1}},"key":"W3vR83bWBu"}],"key":"wAoBBj1lFM"}],"key":"EDQ3CoWGXX"},{"type":"block","kind":"notebook-code","children":[{"type":"code","lang":"python","executable":true,"value":"print(cat.session_log())","key":"lY5krlgn5T"},{"type":"output","id":"OQu0dLYw6PFxe6Yl0TMHI","data":[{"output_type":"stream","name":"stdout","text":"\u001b[36;20m2025-06-17 21:41:57 \u001b[0m└─SolrESGFIndex('esgf-node.ornl.gov') \u001b[91;20mno response\u001b[0m\n\u001b[36;20m2025-06-17 21:41:58 \u001b[0m└─GlobusESGFIndex('anl-dev') results=9 response_time=0.49\n\u001b[36;20m2025-06-17 21:41:58 \u001b[0m└─GlobusESGFIndex('ornl-dev') results=650 response_time=0.73\n\u001b[36;20m2025-06-17 21:41:58 \u001b[0m\u001b[36;32msearch begin\u001b[0m experiment_id=['historical'], source_id=['CanESM5'], frequency=['mon'], variable_id=['gpp', 'tas', 'pr'], type=['Dataset'], project=['CMIP6'], latest=[True], retracted=[False]\n\u001b[36;20m2025-06-17 21:41:58 \u001b[0m└─GlobusESGFIndex('ESGF2-US-1.5-Catalog') results=1396 response_time=1.02\n\u001b[36;20m2025-06-17 21:41:58 \u001b[0m└─GlobusESGFIndex('anl-dev') results=0 response_time=0.09\n\u001b[36;20m2025-06-17 21:41:59 \u001b[0m└─GlobusESGFIndex('ornl-dev') results=410 response_time=0.36\n\u001b[36;20m2025-06-17 21:41:59 \u001b[0mcombine_time=0.08\n\u001b[36;20m2025-06-17 21:41:59 \u001b[0m\u001b[36;32msearch end\u001b[0m total_time=0.49\n\u001b[36;20m2025-06-17 21:41:59 \u001b[0m\u001b[36;32msearch begin\u001b[0m experiment_id=['historical'], source_id=['CanESM5'], frequency=['mon'], variable_id=['gpp', 'tas', 'pr'], variant_label=['r1i1p1f1'], type=['Dataset'], project=['CMIP6'], latest=[True], retracted=[False]\n\u001b[36;20m2025-06-17 21:41:59 \u001b[0m└─GlobusESGFIndex('ornl-dev') results=8 response_time=0.07\n\u001b[36;20m2025-06-17 21:41:59 \u001b[0m└─GlobusESGFIndex('anl-dev') results=0 response_time=0.08\n\u001b[36;20m2025-06-17 21:41:59 \u001b[0mcombine_time=0.01\n\u001b[36;20m2025-06-17 21:41:59 \u001b[0m\u001b[36;32msearch end\u001b[0m total_time=0.09\n\u001b[36;20m2025-06-17 21:41:59 \u001b[0m\u001b[36;32mfile info begin\u001b[0m\n\u001b[36;20m2025-06-17 21:41:59 \u001b[0m└─GlobusESGFIndex('anl-dev') results=0 response_time=0.06\n\u001b[36;20m2025-06-17 21:41:59 \u001b[0m└─GlobusESGFIndex('ornl-dev') results=8 response_time=0.12\n\u001b[36;20m2025-06-17 21:41:59 \u001b[0mcombine_time=0.00\n\u001b[36;20m2025-06-17 21:41:59 \u001b[0m\u001b[36;32mfile info end\u001b[0m total_time=0.13\n\u001b[36;20m2025-06-17 21:41:59 \u001b[0m\u001b[36;32msearch begin\u001b[0m activity_id=['CMIP'], experiment_id=['historical'], variable_id=['pr'], member_id=['r1i1p1f1'], grid_label=['gn'], table_id=['Amon'], source_id=['CESM2', 'CanESM5'], type=['Dataset'], project=['CMIP6'], latest=[True], retracted=[False]\n\u001b[36;20m2025-06-17 21:41:59 \u001b[0mtransfer_time=0.46 [s] at 41.66 [Mb s-1] http://crd-esgf-drc.ec.gc.ca/thredds/fileServer/esgC_dataroot/AR6/CMIP6/CMIP/CCCma/CanESM5/historical/r1i1p1f1/Lmon/gpp/gn/v20190429/gpp_Lmon_CanESM5_historical_r1i1p1f1_gn_185001-201412.nc\n\u001b[36;20m2025-06-17 21:42:01 \u001b[0m\u001b[36;32msearch begin\u001b[0m experiment_id=['historical'], variable_id=['tos'], table_id=['Omon'], project=['CMIP6'], grid_label=['gn'], source_id=['CAMS-CSM1-0', 'FGOALS-g3', 'CMCC-CM2-SR5', 'CNRM-CM6-1', 'CNRM-ESM2-1', 'CESM2'], type=['Dataset'], latest=[True], retracted=[False]\n\u001b[36;20m2025-06-17 21:42:01 \u001b[0m└─SolrESGFIndex('esgf-node.ipsl.upmc.fr') results=58 response_time=4.09\n\u001b[36;20m2025-06-17 21:42:01 \u001b[0m└─SolrESGFIndex('esg-dn1.nsc.liu.se') results=62 response_time=4.32\n\u001b[36;20m2025-06-17 21:42:04 \u001b[0mtransfer_time=4.66 [s] at 11.26 [Mb s-1] http://esgf-data04.diasjp.net/thredds/fileServer/esg_dataroot/CMIP6/CMIP/CCCma/CanESM5/historical/r1i1p1f1/Amon/tas/gn/v20190429/tas_Amon_CanESM5_historical_r1i1p1f1_gn_185001-201412.nc\n\u001b[36;20m2025-06-17 21:42:04 \u001b[0mtransfer_time=5.12 [s] at 11.72 [Mb s-1] http://esgf-data04.diasjp.net/thredds/fileServer/esg_dataroot/CMIP6/CMIP/CCCma/CanESM5/historical/r1i1p1f1/Amon/pr/gn/v20190429/pr_Amon_CanESM5_historical_r1i1p1f1_gn_185001-201412.nc\n\u001b[36;20m2025-06-17 21:42:04 \u001b[0maccessed /home/runner/.esgf/CMIP6/CMIP/CCCma/CanESM5/historical/r1i1p1f1/Amon/pr/gn/v20190429/pr_Amon_CanESM5_historical_r1i1p1f1_gn_185001-201412.nc\n\u001b[36;20m2025-06-17 21:42:04 \u001b[0maccessed /home/runner/.esgf/CMIP6/CMIP/CCCma/CanESM5/historical/r1i1p1f1/Amon/tas/gn/v20190429/tas_Amon_CanESM5_historical_r1i1p1f1_gn_185001-201412.nc\n\u001b[36;20m2025-06-17 21:42:04 \u001b[0maccessed /home/runner/.esgf/CMIP6/CMIP/CCCma/CanESM5/historical/r1i1p1f1/Lmon/gpp/gn/v20190429/gpp_Lmon_CanESM5_historical_r1i1p1f1_gn_185001-201412.nc\n\u001b[36;20m2025-06-17 21:42:04 \u001b[0m\u001b[36;32msearch begin\u001b[0m source_id=['CanESM5'], institution_id=['CCCma'], activity_drs=['CMIP'], member_id=['r1i1p1f1'], grid_label=['gn'], experiment_id=['historical'], mip_era=['CMIP6'], variable_id=['areacella'], type=['Dataset'], project=['CMIP6'], latest=[True], retracted=[False]\n\u001b[36;20m2025-06-17 21:42:04 \u001b[0m└─GlobusESGFIndex('ornl-dev') results=3 response_time=0.07\n\u001b[36;20m2025-06-17 21:42:04 \u001b[0m└─GlobusESGFIndex('anl-dev') results=0 response_time=0.13\n\u001b[36;20m2025-06-17 21:42:04 \u001b[0mcombine_time=0.00\n\u001b[36;20m2025-06-17 21:42:04 \u001b[0m\u001b[36;32msearch end\u001b[0m total_time=0.14\n\u001b[36;20m2025-06-17 21:42:04 \u001b[0m\u001b[36;32mfile info begin\u001b[0m\n\u001b[36;20m2025-06-17 21:42:05 \u001b[0m└─GlobusESGFIndex('ornl-dev') results=3 response_time=0.06\n\u001b[36;20m2025-06-17 21:42:05 \u001b[0m└─GlobusESGFIndex('anl-dev') results=0 response_time=0.06\n\u001b[36;20m2025-06-17 21:42:05 \u001b[0mcombine_time=0.00\n\u001b[36;20m2025-06-17 21:42:05 \u001b[0m\u001b[36;32mfile info end\u001b[0m total_time=0.06\n\u001b[36;20m2025-06-17 21:42:05 \u001b[0mtransfer_time=0.30 [s] at 0.17 [Mb s-1] http://esgf-node.ornl.gov/thredds/fileServer/css03_data/CMIP6/CMIP/CCCma/CanESM5/historical/r1i1p1f1/fx/areacella/gn/v20190429/areacella_fx_CanESM5_historical_r1i1p1f1_gn.nc\n\u001b[36;20m2025-06-17 21:42:05 \u001b[0maccessed /home/runner/.esgf/CMIP6/CMIP/CCCma/CanESM5/historical/r1i1p1f1/fx/areacella/gn/v20190429/areacella_fx_CanESM5_historical_r1i1p1f1_gn.nc\n\u001b[36;20m2025-06-17 21:42:05 \u001b[0m\u001b[36;32msearch begin\u001b[0m source_id=['CanESM5'], institution_id=['CCCma'], activity_drs=['CMIP'], member_id=['r1i1p1f1'], grid_label=['gn'], experiment_id=['historical'], mip_era=['CMIP6'], variable_id=['areacella'], type=['Dataset'], project=['CMIP6'], latest=[True], retracted=[False]\n\u001b[36;20m2025-06-17 21:42:05 \u001b[0m└─GlobusESGFIndex('anl-dev') results=0 response_time=0.06\n\u001b[36;20m2025-06-17 21:42:05 \u001b[0m└─GlobusESGFIndex('ornl-dev') results=3 response_time=0.18\n\u001b[36;20m2025-06-17 21:42:05 \u001b[0mcombine_time=0.00\n\u001b[36;20m2025-06-17 21:42:05 \u001b[0m\u001b[36;32msearch end\u001b[0m total_time=0.18\n\u001b[36;20m2025-06-17 21:42:05 \u001b[0m\u001b[36;32mfile info begin\u001b[0m\n\u001b[36;20m2025-06-17 21:42:05 \u001b[0m└─GlobusESGFIndex('anl-dev') results=0 response_time=0.05\n\u001b[36;20m2025-06-17 21:42:05 \u001b[0m└─GlobusESGFIndex('ornl-dev') results=3 response_time=0.06\n\u001b[36;20m2025-06-17 21:42:05 \u001b[0mcombine_time=0.00\n\u001b[36;20m2025-06-17 21:42:05 \u001b[0m\u001b[36;32mfile info end\u001b[0m total_time=0.06\n\u001b[36;20m2025-06-17 21:42:05 \u001b[0maccessed /home/runner/.esgf/CMIP6/CMIP/CCCma/CanESM5/historical/r1i1p1f1/fx/areacella/gn/v20190429/areacella_fx_CanESM5_historical_r1i1p1f1_gn.nc\n\u001b[36;20m2025-06-17 21:42:05 \u001b[0m\u001b[36;32msearch begin\u001b[0m source_id=['CanESM5'], institution_id=['CCCma'], activity_drs=['CMIP'], member_id=['r1i1p1f1'], grid_label=['gn'], experiment_id=['historical'], mip_era=['CMIP6'], variable_id=['sftlf'], type=['Dataset'], project=['CMIP6'], latest=[True], retracted=[False]\n\u001b[36;20m2025-06-17 21:42:05 \u001b[0m└─GlobusESGFIndex('anl-dev') results=0 response_time=0.06\n\u001b[36;20m2025-06-17 21:42:05 \u001b[0m└─GlobusESGFIndex('ornl-dev') results=3 response_time=0.10\n\u001b[36;20m2025-06-17 21:42:05 \u001b[0mcombine_time=0.00\n\u001b[36;20m2025-06-17 21:42:05 \u001b[0m\u001b[36;32msearch end\u001b[0m total_time=0.10\n\u001b[36;20m2025-06-17 21:42:05 \u001b[0m\u001b[36;32mfile info begin\u001b[0m\n\u001b[36;20m2025-06-17 21:42:05 \u001b[0m└─GlobusESGFIndex('ornl-dev') results=3 response_time=0.05\n\u001b[36;20m2025-06-17 21:42:05 \u001b[0m└─GlobusESGFIndex('anl-dev') results=0 response_time=0.06\n\u001b[36;20m2025-06-17 21:42:05 \u001b[0mcombine_time=0.00\n\u001b[36;20m2025-06-17 21:42:05 \u001b[0m\u001b[36;32mfile info end\u001b[0m total_time=0.06\n\u001b[36;20m2025-06-17 21:42:06 \u001b[0mtransfer_time=0.29 [s] at 0.21 [Mb s-1] http://esgf-node.ornl.gov/thredds/fileServer/css03_data/CMIP6/CMIP/CCCma/CanESM5/historical/r1i1p1f1/fx/sftlf/gn/v20190429/sftlf_fx_CanESM5_historical_r1i1p1f1_gn.nc\n\u001b[36;20m2025-06-17 21:42:06 \u001b[0maccessed /home/runner/.esgf/CMIP6/CMIP/CCCma/CanESM5/historical/r1i1p1f1/fx/sftlf/gn/v20190429/sftlf_fx_CanESM5_historical_r1i1p1f1_gn.nc\n\u001b[36;20m2025-06-17 21:42:06 \u001b[0m\u001b[36;32msearch begin\u001b[0m source_id=['CanESM5'], institution_id=['CCCma'], activity_drs=['CMIP'], member_id=['r1i1p1f1'], grid_label=['gn'], experiment_id=['historical'], mip_era=['CMIP6'], variable_id=['areacella'], type=['Dataset'], project=['CMIP6'], latest=[True], retracted=[False]\n\u001b[36;20m2025-06-17 21:42:06 \u001b[0m└─GlobusESGFIndex('anl-dev') results=0 response_time=0.06\n\u001b[36;20m2025-06-17 21:42:06 \u001b[0m└─GlobusESGFIndex('ornl-dev') results=3 response_time=0.06\n\u001b[36;20m2025-06-17 21:42:06 \u001b[0mcombine_time=0.00\n\u001b[36;20m2025-06-17 21:42:06 \u001b[0m\u001b[36;32msearch end\u001b[0m total_time=0.07\n\u001b[36;20m2025-06-17 21:42:06 \u001b[0m\u001b[36;32mfile info begin\u001b[0m\n\u001b[36;20m2025-06-17 21:42:06 \u001b[0m└─GlobusESGFIndex('ornl-dev') results=3 response_time=0.05\n\u001b[36;20m2025-06-17 21:42:06 \u001b[0m└─GlobusESGFIndex('anl-dev') results=0 response_time=0.06\n\u001b[36;20m2025-06-17 21:42:06 \u001b[0mcombine_time=0.00\n\u001b[36;20m2025-06-17 21:42:06 \u001b[0m\u001b[36;32mfile info end\u001b[0m total_time=0.06\n\u001b[36;20m2025-06-17 21:42:06 \u001b[0maccessed /home/runner/.esgf/CMIP6/CMIP/CCCma/CanESM5/historical/r1i1p1f1/fx/areacella/gn/v20190429/areacella_fx_CanESM5_historical_r1i1p1f1_gn.nc\n\u001b[36;20m2025-06-17 21:42:11 \u001b[0m└─SolrESGFIndex('esgf-data.dkrz.de') results=266 response_time=13.66\n\u001b[36;20m2025-06-17 21:42:14 \u001b[0m└─SolrESGFIndex('esgf.ceda.ac.uk') results=231 response_time=17.07\n\u001b[36;20m2025-06-17 21:42:23 \u001b[0m└─SolrESGFIndex('esgf-node.llnl.gov') \u001b[91;20mno response\u001b[0m\n\u001b[36;20m2025-06-17 21:42:23 \u001b[0m\u001b[36;32msearch end \u001b[91;20mno results\u001b[0m\n\u001b[36;20m2025-06-17 21:42:25 \u001b[0m└─SolrESGFIndex('esgf.nci.org.au') results=211 response_time=27.49\n\u001b[36;20m2025-06-17 21:43:29 \u001b[0m└─SolrESGFIndex('esgf-node.llnl.gov') \u001b[91;20mno response\u001b[0m\n\u001b[36;20m2025-06-17 21:43:29 \u001b[0mcombine_time=0.16\n\u001b[36;20m2025-06-17 21:43:29 \u001b[0m\u001b[36;32msearch end\u001b[0m total_time=92.08\n\n"}],"key":"jpj8a6AuZv"}],"key":"q14Y0ZVu6E"},{"type":"block","kind":"notebook-content","children":[{"type":"paragraph","position":{"start":{"line":1,"column":1},"end":{"line":1,"column":1}},"children":[{"type":"text","value":"At this stage of the search you have a catalog full of possibly relevant datasets for your analysis, stored in a ","position":{"start":{"line":1,"column":1},"end":{"line":1,"column":1}},"key":"dCiNV3DEie"},{"type":"inlineCode","value":"pandas","position":{"start":{"line":1,"column":1},"end":{"line":1,"column":1}},"key":"fjaKqwJrYX"},{"type":"text","value":" dataframe. You are free to view and manipulate this dataframe to help hone these results down. It is available to you as the ","position":{"start":{"line":1,"column":1},"end":{"line":1,"column":1}},"key":"IZoZ2jHC9D"},{"type":"inlineCode","value":"df","position":{"start":{"line":1,"column":1},"end":{"line":1,"column":1}},"key":"j6d96fMqid"},{"type":"text","value":" member of the ","position":{"start":{"line":1,"column":1},"end":{"line":1,"column":1}},"key":"ZdXiRZIDsj"},{"type":"inlineCode","value":"ESGFCatalog","position":{"start":{"line":1,"column":1},"end":{"line":1,"column":1}},"key":"p7JZE8hwMG"},{"type":"text","value":". You should be careful to only remove rows as internally we could use any column in the downloading of the data. Also note that we have removed the user-facing notion of ","position":{"start":{"line":1,"column":1},"end":{"line":1,"column":1}},"key":"e6SKFTrrmB"},{"type":"emphasis","position":{"start":{"line":1,"column":1},"end":{"line":1,"column":1}},"children":[{"type":"text","value":"where","position":{"start":{"line":1,"column":1},"end":{"line":1,"column":1}},"key":"pKf13IW55Q"}],"key":"VAheU3GxCK"},{"type":"text","value":" the data is hosted. The ","position":{"start":{"line":1,"column":1},"end":{"line":1,"column":1}},"key":"WGKanshL9J"},{"type":"inlineCode","value":"id","position":{"start":{"line":1,"column":1},"end":{"line":1,"column":1}},"key":"OAYAkEgWjq"},{"type":"text","value":" column of this dataframe is a list of full ","position":{"start":{"line":1,"column":1},"end":{"line":1,"column":1}},"key":"So5wOGNfHi"},{"type":"inlineCode","value":"dataset_ids","position":{"start":{"line":1,"column":1},"end":{"line":1,"column":1}},"key":"w6u2gxyXNj"},{"type":"text","value":" which includes the location information. At the point when you are ready to download data, we will choose locations automatically that are fastest for you.","position":{"start":{"line":1,"column":1},"end":{"line":1,"column":1}},"key":"Lo4kCyQJ9I"}],"key":"ljaNGFDFEf"}],"key":"aFUPqdlRR8"},{"type":"block","kind":"notebook-code","children":[{"type":"code","lang":"python","executable":true,"value":"cat.df","key":"Px9YUkMMEt"},{"type":"output","id":"hqwDTyyFmLuNIOS479Ut9","data":[{"output_type":"execute_result","execution_count":6,"metadata":{},"data":{"text/plain":{"content":"     project mip_era activity_drs       institution_id          source_id  \\\n0      CMIP6   CMIP6         CMIP                 NCAR    CESM2-WACCM-FV2   \n1      CMIP6   CMIP6         CMIP                 NCAR          CESM2-FV2   \n2      CMIP6   CMIP6         CMIP                MIROC         MIROC-ES2H   \n3      CMIP6   CMIP6         CMIP  EC-Earth-Consortium  EC-Earth3-AerChem   \n4      CMIP6   CMIP6         CMIP                 NCAR          CESM2-FV2   \n...      ...     ...          ...                  ...                ...   \n1515   CMIP6   CMIP6         CMIP  EC-Earth-Consortium      EC-Earth3-Veg   \n1516   CMIP6   CMIP6         CMIP  EC-Earth-Consortium      EC-Earth3-Veg   \n1519   CMIP6   CMIP6         CMIP  EC-Earth-Consortium    EC-Earth3-ESM-1   \n1520   CMIP6   CMIP6         CMIP  EC-Earth-Consortium    EC-Earth3-ESM-1   \n1787   CMIP6   CMIP6         CMIP                  AWI    AWI-ESM-1-REcoM   \n\n     experiment_id member_id table_id variable_id grid_label   version  \\\n0        piControl  r1i2p2f1     Lmon         nbp         gn  20220915   \n1          1pctCO2  r1i2p2f1     Lmon         nbp         gn  20220915   \n2        piControl  r1i1p4f2     Omon       fgco2         gn  20220322   \n3        piControl  r1i1p1f1     Amon         tas         gr  20220621   \n4        piControl  r1i2p2f1     Amon         tas         gn  20220915   \n...            ...       ...      ...         ...        ...       ...   \n1515     piControl  r3i1p1f1     Lmon         nbp         gr  20231010   \n1516     piControl  r3i1p1f1     Amon         tas         gr  20231010   \n1519     piControl  r1i1p1f1     Lmon         nbp         gr  20240925   \n1520     piControl  r1i1p1f1     Omon       fgco2         gn  20240925   \n1787     piControl  r1i1p1f1     Amon         tas         gn  20230314   \n\n                                                     id  \n0     [CMIP6.CMIP.NCAR.CESM2-WACCM-FV2.piControl.r1i...  \n1     [CMIP6.CMIP.NCAR.CESM2-FV2.1pctCO2.r1i2p2f1.Lm...  \n2     [CMIP6.CMIP.MIROC.MIROC-ES2H.piControl.r1i1p4f...  \n3     [CMIP6.CMIP.EC-Earth-Consortium.EC-Earth3-AerC...  \n4     [CMIP6.CMIP.NCAR.CESM2-FV2.piControl.r1i2p2f1....  \n...                                                 ...  \n1515  [CMIP6.CMIP.EC-Earth-Consortium.EC-Earth3-Veg....  \n1516  [CMIP6.CMIP.EC-Earth-Consortium.EC-Earth3-Veg....  \n1519  [CMIP6.CMIP.EC-Earth-Consortium.EC-Earth3-ESM-...  \n1520  [CMIP6.CMIP.EC-Earth-Consortium.EC-Earth3-ESM-...  \n1787  [CMIP6.CMIP.AWI.AWI-ESM-1-REcoM.piControl.r1i1...  \n\n[424 rows x 12 columns]","content_type":"text/plain"},"text/html":{"content":"<div>\n<style scoped>\n    .dataframe tbody tr th:only-of-type {\n        vertical-align: middle;\n    }\n\n    .dataframe tbody tr th {\n        vertical-align: top;\n    }\n\n    .dataframe thead th {\n        text-align: right;\n    }\n</style>\n<table border=\"1\" class=\"dataframe\">\n  <thead>\n    <tr style=\"text-align: right;\">\n      <th></th>\n      <th>project</th>\n      <th>mip_era</th>\n      <th>activity_drs</th>\n      <th>institution_id</th>\n      <th>source_id</th>\n      <th>experiment_id</th>\n      <th>member_id</th>\n      <th>table_id</th>\n      <th>variable_id</th>\n      <th>grid_label</th>\n      <th>version</th>\n      <th>id</th>\n    </tr>\n  </thead>\n  <tbody>\n    <tr>\n      <th>0</th>\n      <td>CMIP6</td>\n      <td>CMIP6</td>\n      <td>CMIP</td>\n      <td>NCAR</td>\n      <td>CESM2-WACCM-FV2</td>\n      <td>piControl</td>\n      <td>r1i2p2f1</td>\n      <td>Lmon</td>\n      <td>nbp</td>\n      <td>gn</td>\n      <td>20220915</td>\n      <td>[CMIP6.CMIP.NCAR.CESM2-WACCM-FV2.piControl.r1i...</td>\n    </tr>\n    <tr>\n      <th>1</th>\n      <td>CMIP6</td>\n      <td>CMIP6</td>\n      <td>CMIP</td>\n      <td>NCAR</td>\n      <td>CESM2-FV2</td>\n      <td>1pctCO2</td>\n      <td>r1i2p2f1</td>\n      <td>Lmon</td>\n      <td>nbp</td>\n      <td>gn</td>\n      <td>20220915</td>\n      <td>[CMIP6.CMIP.NCAR.CESM2-FV2.1pctCO2.r1i2p2f1.Lm...</td>\n    </tr>\n    <tr>\n      <th>2</th>\n      <td>CMIP6</td>\n      <td>CMIP6</td>\n      <td>CMIP</td>\n      <td>MIROC</td>\n      <td>MIROC-ES2H</td>\n      <td>piControl</td>\n      <td>r1i1p4f2</td>\n      <td>Omon</td>\n      <td>fgco2</td>\n      <td>gn</td>\n      <td>20220322</td>\n      <td>[CMIP6.CMIP.MIROC.MIROC-ES2H.piControl.r1i1p4f...</td>\n    </tr>\n    <tr>\n      <th>3</th>\n      <td>CMIP6</td>\n      <td>CMIP6</td>\n      <td>CMIP</td>\n      <td>EC-Earth-Consortium</td>\n      <td>EC-Earth3-AerChem</td>\n      <td>piControl</td>\n      <td>r1i1p1f1</td>\n      <td>Amon</td>\n      <td>tas</td>\n      <td>gr</td>\n      <td>20220621</td>\n      <td>[CMIP6.CMIP.EC-Earth-Consortium.EC-Earth3-AerC...</td>\n    </tr>\n    <tr>\n      <th>4</th>\n      <td>CMIP6</td>\n      <td>CMIP6</td>\n      <td>CMIP</td>\n      <td>NCAR</td>\n      <td>CESM2-FV2</td>\n      <td>piControl</td>\n      <td>r1i2p2f1</td>\n      <td>Amon</td>\n      <td>tas</td>\n      <td>gn</td>\n      <td>20220915</td>\n      <td>[CMIP6.CMIP.NCAR.CESM2-FV2.piControl.r1i2p2f1....</td>\n    </tr>\n    <tr>\n      <th>...</th>\n      <td>...</td>\n      <td>...</td>\n      <td>...</td>\n      <td>...</td>\n      <td>...</td>\n      <td>...</td>\n      <td>...</td>\n      <td>...</td>\n      <td>...</td>\n      <td>...</td>\n      <td>...</td>\n      <td>...</td>\n    </tr>\n    <tr>\n      <th>1515</th>\n      <td>CMIP6</td>\n      <td>CMIP6</td>\n      <td>CMIP</td>\n      <td>EC-Earth-Consortium</td>\n      <td>EC-Earth3-Veg</td>\n      <td>piControl</td>\n      <td>r3i1p1f1</td>\n      <td>Lmon</td>\n      <td>nbp</td>\n      <td>gr</td>\n      <td>20231010</td>\n      <td>[CMIP6.CMIP.EC-Earth-Consortium.EC-Earth3-Veg....</td>\n    </tr>\n    <tr>\n      <th>1516</th>\n      <td>CMIP6</td>\n      <td>CMIP6</td>\n      <td>CMIP</td>\n      <td>EC-Earth-Consortium</td>\n      <td>EC-Earth3-Veg</td>\n      <td>piControl</td>\n      <td>r3i1p1f1</td>\n      <td>Amon</td>\n      <td>tas</td>\n      <td>gr</td>\n      <td>20231010</td>\n      <td>[CMIP6.CMIP.EC-Earth-Consortium.EC-Earth3-Veg....</td>\n    </tr>\n    <tr>\n      <th>1519</th>\n      <td>CMIP6</td>\n      <td>CMIP6</td>\n      <td>CMIP</td>\n      <td>EC-Earth-Consortium</td>\n      <td>EC-Earth3-ESM-1</td>\n      <td>piControl</td>\n      <td>r1i1p1f1</td>\n      <td>Lmon</td>\n      <td>nbp</td>\n      <td>gr</td>\n      <td>20240925</td>\n      <td>[CMIP6.CMIP.EC-Earth-Consortium.EC-Earth3-ESM-...</td>\n    </tr>\n    <tr>\n      <th>1520</th>\n      <td>CMIP6</td>\n      <td>CMIP6</td>\n      <td>CMIP</td>\n      <td>EC-Earth-Consortium</td>\n      <td>EC-Earth3-ESM-1</td>\n      <td>piControl</td>\n      <td>r1i1p1f1</td>\n      <td>Omon</td>\n      <td>fgco2</td>\n      <td>gn</td>\n      <td>20240925</td>\n      <td>[CMIP6.CMIP.EC-Earth-Consortium.EC-Earth3-ESM-...</td>\n    </tr>\n    <tr>\n      <th>1787</th>\n      <td>CMIP6</td>\n      <td>CMIP6</td>\n      <td>CMIP</td>\n      <td>AWI</td>\n      <td>AWI-ESM-1-REcoM</td>\n      <td>piControl</td>\n      <td>r1i1p1f1</td>\n      <td>Amon</td>\n      <td>tas</td>\n      <td>gn</td>\n      <td>20230314</td>\n      <td>[CMIP6.CMIP.AWI.AWI-ESM-1-REcoM.piControl.r1i1...</td>\n    </tr>\n  </tbody>\n</table>\n<p>424 rows × 12 columns</p>\n</div>","content_type":"text/html"}}}],"key":"BUA7wn9uoa"}],"key":"noY7G1Q6KN"},{"type":"block","kind":"notebook-content","children":[{"type":"heading","depth":2,"position":{"start":{"line":1,"column":1},"end":{"line":1,"column":1}},"children":[{"type":"text","value":"Model Groups","position":{"start":{"line":1,"column":1},"end":{"line":1,"column":1}},"key":"YmY4qyKEGG"}],"identifier":"model-groups","label":"Model Groups","html_id":"model-groups","implicit":true,"key":"Wuz7Mgg7Eh"},{"type":"paragraph","position":{"start":{"line":3,"column":1},"end":{"line":3,"column":1}},"children":[{"type":"text","value":"However, ","position":{"start":{"line":3,"column":1},"end":{"line":3,"column":1}},"key":"HkMWUcmY8G"},{"type":"inlineCode","value":"intake-esgf","position":{"start":{"line":3,"column":1},"end":{"line":3,"column":1}},"key":"UaU1BqOBGd"},{"type":"text","value":" also provides you with some tools to help locate relevant data for your analysis. When conducting these kinds of analyses, we are seeking for unique combinations of a ","position":{"start":{"line":3,"column":1},"end":{"line":3,"column":1}},"key":"kpSfEwRQSX"},{"type":"inlineCode","value":"source_id","position":{"start":{"line":3,"column":1},"end":{"line":3,"column":1}},"key":"X2WvOX2NGR"},{"type":"text","value":", ","position":{"start":{"line":3,"column":1},"end":{"line":3,"column":1}},"key":"M6HcaYt5Ko"},{"type":"inlineCode","value":"member_id","position":{"start":{"line":3,"column":1},"end":{"line":3,"column":1}},"key":"pQl2y0rgbQ"},{"type":"text","value":", and ","position":{"start":{"line":3,"column":1},"end":{"line":3,"column":1}},"key":"A46zgvu5sI"},{"type":"inlineCode","value":"grid_label","position":{"start":{"line":3,"column":1},"end":{"line":3,"column":1}},"key":"QO7FVOJpGy"},{"type":"text","value":" that have all the variables that we need. We call these ","position":{"start":{"line":3,"column":1},"end":{"line":3,"column":1}},"key":"qxhgpEklk0"},{"type":"emphasis","position":{"start":{"line":3,"column":1},"end":{"line":3,"column":1}},"children":[{"type":"text","value":"model groups","position":{"start":{"line":3,"column":1},"end":{"line":3,"column":1}},"key":"a6VYJ6WSeu"}],"key":"N2pfy6w8bW"},{"type":"text","value":". In an ESGF search, it is common to find a model that has, for example, a ","position":{"start":{"line":3,"column":1},"end":{"line":3,"column":1}},"key":"jaFgQhYC92"},{"type":"inlineCode","value":"tas","position":{"start":{"line":3,"column":1},"end":{"line":3,"column":1}},"key":"IrvGEMuGI4"},{"type":"text","value":" for ","position":{"start":{"line":3,"column":1},"end":{"line":3,"column":1}},"key":"Ntk74gyzn7"},{"type":"inlineCode","value":"r1i1p1f1","position":{"start":{"line":3,"column":1},"end":{"line":3,"column":1}},"key":"cS0rDB0uyW"},{"type":"text","value":" but not a ","position":{"start":{"line":3,"column":1},"end":{"line":3,"column":1}},"key":"ICkGbKLbIT"},{"type":"inlineCode","value":"fgco2","position":{"start":{"line":3,"column":1},"end":{"line":3,"column":1}},"key":"d7WmDYBTEJ"},{"type":"text","value":". Sorting this out is time consuming and labor intensive. So first, we provide you a function to print out all model groups with the following function.","position":{"start":{"line":3,"column":1},"end":{"line":3,"column":1}},"key":"AZTJdl3FM4"}],"key":"FCh0VL6SpM"}],"key":"DC0nm3TP12"},{"type":"block","kind":"notebook-code","children":[{"type":"code","lang":"python","executable":true,"value":"cat.model_groups().to_frame()","key":"BP6boY8QfV"},{"type":"output","id":"dadgsg7z1ScQE4y-rK-oC","data":[{"output_type":"execute_result","execution_count":7,"metadata":{},"data":{"text/plain":{"content":"                                      project\nsource_id       member_id grid_label         \nACCESS-CM2      r1i1p1f1  gn                2\nACCESS-ESM1-5   r1i1p1f1  gn                6\nAWI-CM-1-1-MR   r1i1p1f1  gn                2\nAWI-ESM-1-1-LR  r1i1p1f1  gn                2\nAWI-ESM-1-REcoM r1i1p1f1  gn                1\n...                                       ...\nUKESM1-0-LL     r1i1p1f2  gn                6\n                r2i1p1f2  gn                3\n                r3i1p1f2  gn                3\n                r4i1p1f2  gn                3\nUKESM1-1-LL     r1i1p1f2  gn                6\n\n[156 rows x 1 columns]","content_type":"text/plain"},"text/html":{"content":"<div>\n<style scoped>\n    .dataframe tbody tr th:only-of-type {\n        vertical-align: middle;\n    }\n\n    .dataframe tbody tr th {\n        vertical-align: top;\n    }\n\n    .dataframe thead th {\n        text-align: right;\n    }\n</style>\n<table border=\"1\" class=\"dataframe\">\n  <thead>\n    <tr style=\"text-align: right;\">\n      <th></th>\n      <th></th>\n      <th></th>\n      <th>project</th>\n    </tr>\n    <tr>\n      <th>source_id</th>\n      <th>member_id</th>\n      <th>grid_label</th>\n      <th></th>\n    </tr>\n  </thead>\n  <tbody>\n    <tr>\n      <th>ACCESS-CM2</th>\n      <th>r1i1p1f1</th>\n      <th>gn</th>\n      <td>2</td>\n    </tr>\n    <tr>\n      <th>ACCESS-ESM1-5</th>\n      <th>r1i1p1f1</th>\n      <th>gn</th>\n      <td>6</td>\n    </tr>\n    <tr>\n      <th>AWI-CM-1-1-MR</th>\n      <th>r1i1p1f1</th>\n      <th>gn</th>\n      <td>2</td>\n    </tr>\n    <tr>\n      <th>AWI-ESM-1-1-LR</th>\n      <th>r1i1p1f1</th>\n      <th>gn</th>\n      <td>2</td>\n    </tr>\n    <tr>\n      <th>AWI-ESM-1-REcoM</th>\n      <th>r1i1p1f1</th>\n      <th>gn</th>\n      <td>1</td>\n    </tr>\n    <tr>\n      <th>...</th>\n      <th>...</th>\n      <th>...</th>\n      <td>...</td>\n    </tr>\n    <tr>\n      <th rowspan=\"4\" valign=\"top\">UKESM1-0-LL</th>\n      <th>r1i1p1f2</th>\n      <th>gn</th>\n      <td>6</td>\n    </tr>\n    <tr>\n      <th>r2i1p1f2</th>\n      <th>gn</th>\n      <td>3</td>\n    </tr>\n    <tr>\n      <th>r3i1p1f2</th>\n      <th>gn</th>\n      <td>3</td>\n    </tr>\n    <tr>\n      <th>r4i1p1f2</th>\n      <th>gn</th>\n      <td>3</td>\n    </tr>\n    <tr>\n      <th>UKESM1-1-LL</th>\n      <th>r1i1p1f2</th>\n      <th>gn</th>\n      <td>6</td>\n    </tr>\n  </tbody>\n</table>\n<p>156 rows × 1 columns</p>\n</div>","content_type":"text/html"}}}],"key":"r741XwPbnz"}],"key":"nZVcC09vZb"},{"type":"block","kind":"notebook-content","children":[{"type":"paragraph","position":{"start":{"line":1,"column":1},"end":{"line":1,"column":1}},"children":[{"type":"text","value":"The function ","position":{"start":{"line":1,"column":1},"end":{"line":1,"column":1}},"key":"RvwqbHp5nv"},{"type":"inlineCode","value":"model_groups()","position":{"start":{"line":1,"column":1},"end":{"line":1,"column":1}},"key":"nwouMEEGCE"},{"type":"text","value":" returns a pandas Series (converted to a dataframe here for printing) with all unique combinations of (","position":{"start":{"line":1,"column":1},"end":{"line":1,"column":1}},"key":"AFuNAcSZ6g"},{"type":"inlineCode","value":"source_id","position":{"start":{"line":1,"column":1},"end":{"line":1,"column":1}},"key":"AJEtDOobHS"},{"type":"text","value":",","position":{"start":{"line":1,"column":1},"end":{"line":1,"column":1}},"key":"p7LrKeA0vl"},{"type":"inlineCode","value":"member_id","position":{"start":{"line":1,"column":1},"end":{"line":1,"column":1}},"key":"RZNe4RtTEf"},{"type":"text","value":",","position":{"start":{"line":1,"column":1},"end":{"line":1,"column":1}},"key":"qopfsQRsZq"},{"type":"inlineCode","value":"grid_label","position":{"start":{"line":1,"column":1},"end":{"line":1,"column":1}},"key":"zd3ZKdEOr0"},{"type":"text","value":") along with the dataset count for each. This helps illustrate why it can be so difficult to locate all the data relevant to a given analysis. At the time of this writing, there are 148 model groups but relatively few of them with all 6 (2 experiments and 3 variables) datasets that we need. Furthermore, you cannot rely on a model group using ","position":{"start":{"line":1,"column":1},"end":{"line":1,"column":1}},"key":"fXTEVQbBtG"},{"type":"inlineCode","value":"r1i1p1f1","position":{"start":{"line":1,"column":1},"end":{"line":1,"column":1}},"key":"UpGzXJ5sUP"},{"type":"text","value":" for its primary result. The results above show that UKESM does not even use ","position":{"start":{"line":1,"column":1},"end":{"line":1,"column":1}},"key":"OiHG7pkPq6"},{"type":"inlineCode","value":"f1","position":{"start":{"line":1,"column":1},"end":{"line":1,"column":1}},"key":"zlWBFmpZH4"},{"type":"text","value":" at all, further complicating the process of finding results.","position":{"start":{"line":1,"column":1},"end":{"line":1,"column":1}},"key":"OnCCvVdd56"}],"key":"uToxU9Y1wB"},{"type":"paragraph","position":{"start":{"line":3,"column":1},"end":{"line":3,"column":1}},"children":[{"type":"text","value":"In addition to this notion of ","position":{"start":{"line":3,"column":1},"end":{"line":3,"column":1}},"key":"jxK54RWahK"},{"type":"emphasis","position":{"start":{"line":3,"column":1},"end":{"line":3,"column":1}},"children":[{"type":"text","value":"model groups","position":{"start":{"line":3,"column":1},"end":{"line":3,"column":1}},"key":"U2Kv3wVkeb"}],"key":"RNnrlxMZw6"},{"type":"text","value":", ","position":{"start":{"line":3,"column":1},"end":{"line":3,"column":1}},"key":"U50C9hcZKU"},{"type":"inlineCode","value":"intake-esgf","position":{"start":{"line":3,"column":1},"end":{"line":3,"column":1}},"key":"ImVnh1Gtr1"},{"type":"text","value":" provides you a method ","position":{"start":{"line":3,"column":1},"end":{"line":3,"column":1}},"key":"E2QZbpAtWT"},{"type":"inlineCode","value":"remove_incomplete()","position":{"start":{"line":3,"column":1},"end":{"line":3,"column":1}},"key":"jms5xGyCnl"},{"type":"text","value":" for determing which model groups you wish to keep in the current search. Internally, we will group the search results dataframe by model groups and apply a function of your design to the grouped portion of the dataframe. For example, for the current work, I could just check that there are 6 datasets in the sub-dataframe.","position":{"start":{"line":3,"column":1},"end":{"line":3,"column":1}},"key":"LXxZOCiRMy"}],"key":"bcVf3BocF0"}],"key":"UWSWPZTaTT"},{"type":"block","kind":"notebook-code","children":[{"type":"code","lang":"python","executable":true,"value":"def shall_i_keep_it(sub_df):\n    if len(sub_df) == 6:\n        return True\n    return False\n\n\ncat.remove_incomplete(shall_i_keep_it)\ncat.model_groups().to_frame()","key":"ldtntJqOPb"},{"type":"output","id":"sUkwNfBBpZJko4TYSRfRx","data":[{"output_type":"execute_result","execution_count":8,"metadata":{},"data":{"text/plain":{"content":"                                       project\nsource_id       member_id  grid_label         \nACCESS-ESM1-5   r1i1p1f1   gn                6\nCanESM5         r1i1p1f1   gn                6\n                r1i1p2f1   gn                6\nCanESM5-1       r1i1p1f1   gn                6\n                r1i1p2f1   gn                6\nCanESM5-CanOE   r1i1p2f1   gn                6\nCESM2           r1i1p1f1   gn                6\nCESM2-FV2       r1i1p1f1   gn                6\nCESM2-WACCM     r1i1p1f1   gn                6\nCESM2-WACCM-FV2 r1i1p1f1   gn                6\nCMCC-ESM2       r1i1p1f1   gn                6\nGISS-E2-1-G     r101i1p1f1 gn                6\n                r102i1p1f1 gn                6\nINM-CM4-8       r1i1p1f1   gr1               6\nINM-CM5-0       r1i1p1f1   gr1               6\nMIROC-ES2L      r1i1p1f2   gn                6\nMPI-ESM-1-2-HAM r1i1p1f1   gn                6\nMPI-ESM1-2-LR   r1i1p1f1   gn                6\nMRI-ESM2-0      r1i2p1f1   gn                6\nNorCPM1         r1i1p1f1   gn                6\nNorESM2-LM      r1i1p1f1   gn                6\n                r1i1p4f1   gn                6\nNorESM2-MM      r1i1p1f1   gn                6\nUKESM1-0-LL     r1i1p1f2   gn                6\nUKESM1-1-LL     r1i1p1f2   gn                6","content_type":"text/plain"},"text/html":{"content":"<div>\n<style scoped>\n    .dataframe tbody tr th:only-of-type {\n        vertical-align: middle;\n    }\n\n    .dataframe tbody tr th {\n        vertical-align: top;\n    }\n\n    .dataframe thead th {\n        text-align: right;\n    }\n</style>\n<table border=\"1\" class=\"dataframe\">\n  <thead>\n    <tr style=\"text-align: right;\">\n      <th></th>\n      <th></th>\n      <th></th>\n      <th>project</th>\n    </tr>\n    <tr>\n      <th>source_id</th>\n      <th>member_id</th>\n      <th>grid_label</th>\n      <th></th>\n    </tr>\n  </thead>\n  <tbody>\n    <tr>\n      <th>ACCESS-ESM1-5</th>\n      <th>r1i1p1f1</th>\n      <th>gn</th>\n      <td>6</td>\n    </tr>\n    <tr>\n      <th rowspan=\"2\" valign=\"top\">CanESM5</th>\n      <th>r1i1p1f1</th>\n      <th>gn</th>\n      <td>6</td>\n    </tr>\n    <tr>\n      <th>r1i1p2f1</th>\n      <th>gn</th>\n      <td>6</td>\n    </tr>\n    <tr>\n      <th rowspan=\"2\" valign=\"top\">CanESM5-1</th>\n      <th>r1i1p1f1</th>\n      <th>gn</th>\n      <td>6</td>\n    </tr>\n    <tr>\n      <th>r1i1p2f1</th>\n      <th>gn</th>\n      <td>6</td>\n    </tr>\n    <tr>\n      <th>CanESM5-CanOE</th>\n      <th>r1i1p2f1</th>\n      <th>gn</th>\n      <td>6</td>\n    </tr>\n    <tr>\n      <th>CESM2</th>\n      <th>r1i1p1f1</th>\n      <th>gn</th>\n      <td>6</td>\n    </tr>\n    <tr>\n      <th>CESM2-FV2</th>\n      <th>r1i1p1f1</th>\n      <th>gn</th>\n      <td>6</td>\n    </tr>\n    <tr>\n      <th>CESM2-WACCM</th>\n      <th>r1i1p1f1</th>\n      <th>gn</th>\n      <td>6</td>\n    </tr>\n    <tr>\n      <th>CESM2-WACCM-FV2</th>\n      <th>r1i1p1f1</th>\n      <th>gn</th>\n      <td>6</td>\n    </tr>\n    <tr>\n      <th>CMCC-ESM2</th>\n      <th>r1i1p1f1</th>\n      <th>gn</th>\n      <td>6</td>\n    </tr>\n    <tr>\n      <th rowspan=\"2\" valign=\"top\">GISS-E2-1-G</th>\n      <th>r101i1p1f1</th>\n      <th>gn</th>\n      <td>6</td>\n    </tr>\n    <tr>\n      <th>r102i1p1f1</th>\n      <th>gn</th>\n      <td>6</td>\n    </tr>\n    <tr>\n      <th>INM-CM4-8</th>\n      <th>r1i1p1f1</th>\n      <th>gr1</th>\n      <td>6</td>\n    </tr>\n    <tr>\n      <th>INM-CM5-0</th>\n      <th>r1i1p1f1</th>\n      <th>gr1</th>\n      <td>6</td>\n    </tr>\n    <tr>\n      <th>MIROC-ES2L</th>\n      <th>r1i1p1f2</th>\n      <th>gn</th>\n      <td>6</td>\n    </tr>\n    <tr>\n      <th>MPI-ESM-1-2-HAM</th>\n      <th>r1i1p1f1</th>\n      <th>gn</th>\n      <td>6</td>\n    </tr>\n    <tr>\n      <th>MPI-ESM1-2-LR</th>\n      <th>r1i1p1f1</th>\n      <th>gn</th>\n      <td>6</td>\n    </tr>\n    <tr>\n      <th>MRI-ESM2-0</th>\n      <th>r1i2p1f1</th>\n      <th>gn</th>\n      <td>6</td>\n    </tr>\n    <tr>\n      <th>NorCPM1</th>\n      <th>r1i1p1f1</th>\n      <th>gn</th>\n      <td>6</td>\n    </tr>\n    <tr>\n      <th rowspan=\"2\" valign=\"top\">NorESM2-LM</th>\n      <th>r1i1p1f1</th>\n      <th>gn</th>\n      <td>6</td>\n    </tr>\n    <tr>\n      <th>r1i1p4f1</th>\n      <th>gn</th>\n      <td>6</td>\n    </tr>\n    <tr>\n      <th>NorESM2-MM</th>\n      <th>r1i1p1f1</th>\n      <th>gn</th>\n      <td>6</td>\n    </tr>\n    <tr>\n      <th>UKESM1-0-LL</th>\n      <th>r1i1p1f2</th>\n      <th>gn</th>\n      <td>6</td>\n    </tr>\n    <tr>\n      <th>UKESM1-1-LL</th>\n      <th>r1i1p1f2</th>\n      <th>gn</th>\n      <td>6</td>\n    </tr>\n  </tbody>\n</table>\n</div>","content_type":"text/html"}}}],"key":"vO5Qkl4u2K"}],"key":"qQUFYekjMF"},{"type":"block","kind":"notebook-content","children":[{"type":"paragraph","position":{"start":{"line":1,"column":1},"end":{"line":1,"column":1}},"children":[{"type":"text","value":"You could write a much more complex check--it depends on what is relevant to your analysis. The effect is that the list of possible models with consistent results is now much more manageable. This method has the added benefit of forcing the user to be concrete about which models were included in an analysis.","position":{"start":{"line":1,"column":1},"end":{"line":1,"column":1}},"key":"bE2ymcJIk3"}],"key":"Df176iMLsN"},{"type":"heading","depth":2,"position":{"start":{"line":3,"column":1},"end":{"line":3,"column":1}},"children":[{"type":"text","value":"Removing Additional Variants","position":{"start":{"line":3,"column":1},"end":{"line":3,"column":1}},"key":"iq5PnNBmFu"}],"identifier":"removing-additional-variants","label":"Removing Additional Variants","html_id":"removing-additional-variants","implicit":true,"key":"Tk6pX7B9IT"},{"type":"paragraph","position":{"start":{"line":5,"column":1},"end":{"line":5,"column":1}},"children":[{"type":"text","value":"It may also be that you wish to only include a single ","position":{"start":{"line":5,"column":1},"end":{"line":5,"column":1}},"key":"FqytHjvZDV"},{"type":"inlineCode","value":"member_id","position":{"start":{"line":5,"column":1},"end":{"line":5,"column":1}},"key":"pgxSQCDFzk"},{"type":"text","value":" in your analysis. The above search shows we have a few models with multiple variants that have all 6 required datasets. To be fair to those that only have 1, you may wish to only keep the ","position":{"start":{"line":5,"column":1},"end":{"line":5,"column":1}},"key":"YG8U0QdksN"},{"type":"emphasis","position":{"start":{"line":5,"column":1},"end":{"line":5,"column":1}},"children":[{"type":"text","value":"smallest","position":{"start":{"line":5,"column":1},"end":{"line":5,"column":1}},"key":"tIFT1TwqFY"}],"key":"hN8fHZJFJr"},{"type":"text","value":" variant. We also provide this function as part of the ","position":{"start":{"line":5,"column":1},"end":{"line":5,"column":1}},"key":"hiluTOW5Nn"},{"type":"inlineCode","value":"ESGFCatalog","position":{"start":{"line":5,"column":1},"end":{"line":5,"column":1}},"key":"RqhbTq2Nhq"},{"type":"text","value":" object.","position":{"start":{"line":5,"column":1},"end":{"line":5,"column":1}},"key":"nDb7NcnvUE"}],"key":"JvfkwGybhn"}],"key":"DcfoPs8f9V"},{"type":"block","kind":"notebook-code","children":[{"type":"code","lang":"python","executable":true,"value":"cat.remove_ensembles()\ncat.model_groups().to_frame()","key":"EYPoa2phoK"},{"type":"output","id":"dG_mglsFpcHKA9tYtbbWe","data":[{"output_type":"execute_result","execution_count":9,"metadata":{},"data":{"text/plain":{"content":"                                       project\nsource_id       member_id  grid_label         \nACCESS-ESM1-5   r1i1p1f1   gn                6\nCanESM5         r1i1p1f1   gn                6\nCanESM5-1       r1i1p1f1   gn                6\nCanESM5-CanOE   r1i1p2f1   gn                6\nCESM2           r1i1p1f1   gn                6\nCESM2-FV2       r1i1p1f1   gn                6\nCESM2-WACCM     r1i1p1f1   gn                6\nCESM2-WACCM-FV2 r1i1p1f1   gn                6\nCMCC-ESM2       r1i1p1f1   gn                6\nGISS-E2-1-G     r101i1p1f1 gn                6\nINM-CM4-8       r1i1p1f1   gr1               6\nINM-CM5-0       r1i1p1f1   gr1               6\nMIROC-ES2L      r1i1p1f2   gn                6\nMPI-ESM-1-2-HAM r1i1p1f1   gn                6\nMPI-ESM1-2-LR   r1i1p1f1   gn                6\nMRI-ESM2-0      r1i2p1f1   gn                6\nNorCPM1         r1i1p1f1   gn                6\nNorESM2-LM      r1i1p1f1   gn                6\nNorESM2-MM      r1i1p1f1   gn                6\nUKESM1-0-LL     r1i1p1f2   gn                6\nUKESM1-1-LL     r1i1p1f2   gn                6","content_type":"text/plain"},"text/html":{"content":"<div>\n<style scoped>\n    .dataframe tbody tr th:only-of-type {\n        vertical-align: middle;\n    }\n\n    .dataframe tbody tr th {\n        vertical-align: top;\n    }\n\n    .dataframe thead th {\n        text-align: right;\n    }\n</style>\n<table border=\"1\" class=\"dataframe\">\n  <thead>\n    <tr style=\"text-align: right;\">\n      <th></th>\n      <th></th>\n      <th></th>\n      <th>project</th>\n    </tr>\n    <tr>\n      <th>source_id</th>\n      <th>member_id</th>\n      <th>grid_label</th>\n      <th></th>\n    </tr>\n  </thead>\n  <tbody>\n    <tr>\n      <th>ACCESS-ESM1-5</th>\n      <th>r1i1p1f1</th>\n      <th>gn</th>\n      <td>6</td>\n    </tr>\n    <tr>\n      <th>CanESM5</th>\n      <th>r1i1p1f1</th>\n      <th>gn</th>\n      <td>6</td>\n    </tr>\n    <tr>\n      <th>CanESM5-1</th>\n      <th>r1i1p1f1</th>\n      <th>gn</th>\n      <td>6</td>\n    </tr>\n    <tr>\n      <th>CanESM5-CanOE</th>\n      <th>r1i1p2f1</th>\n      <th>gn</th>\n      <td>6</td>\n    </tr>\n    <tr>\n      <th>CESM2</th>\n      <th>r1i1p1f1</th>\n      <th>gn</th>\n      <td>6</td>\n    </tr>\n    <tr>\n      <th>CESM2-FV2</th>\n      <th>r1i1p1f1</th>\n      <th>gn</th>\n      <td>6</td>\n    </tr>\n    <tr>\n      <th>CESM2-WACCM</th>\n      <th>r1i1p1f1</th>\n      <th>gn</th>\n      <td>6</td>\n    </tr>\n    <tr>\n      <th>CESM2-WACCM-FV2</th>\n      <th>r1i1p1f1</th>\n      <th>gn</th>\n      <td>6</td>\n    </tr>\n    <tr>\n      <th>CMCC-ESM2</th>\n      <th>r1i1p1f1</th>\n      <th>gn</th>\n      <td>6</td>\n    </tr>\n    <tr>\n      <th>GISS-E2-1-G</th>\n      <th>r101i1p1f1</th>\n      <th>gn</th>\n      <td>6</td>\n    </tr>\n    <tr>\n      <th>INM-CM4-8</th>\n      <th>r1i1p1f1</th>\n      <th>gr1</th>\n      <td>6</td>\n    </tr>\n    <tr>\n      <th>INM-CM5-0</th>\n      <th>r1i1p1f1</th>\n      <th>gr1</th>\n      <td>6</td>\n    </tr>\n    <tr>\n      <th>MIROC-ES2L</th>\n      <th>r1i1p1f2</th>\n      <th>gn</th>\n      <td>6</td>\n    </tr>\n    <tr>\n      <th>MPI-ESM-1-2-HAM</th>\n      <th>r1i1p1f1</th>\n      <th>gn</th>\n      <td>6</td>\n    </tr>\n    <tr>\n      <th>MPI-ESM1-2-LR</th>\n      <th>r1i1p1f1</th>\n      <th>gn</th>\n      <td>6</td>\n    </tr>\n    <tr>\n      <th>MRI-ESM2-0</th>\n      <th>r1i2p1f1</th>\n      <th>gn</th>\n      <td>6</td>\n    </tr>\n    <tr>\n      <th>NorCPM1</th>\n      <th>r1i1p1f1</th>\n      <th>gn</th>\n      <td>6</td>\n    </tr>\n    <tr>\n      <th>NorESM2-LM</th>\n      <th>r1i1p1f1</th>\n      <th>gn</th>\n      <td>6</td>\n    </tr>\n    <tr>\n      <th>NorESM2-MM</th>\n      <th>r1i1p1f1</th>\n      <th>gn</th>\n      <td>6</td>\n    </tr>\n    <tr>\n      <th>UKESM1-0-LL</th>\n      <th>r1i1p1f2</th>\n      <th>gn</th>\n      <td>6</td>\n    </tr>\n    <tr>\n      <th>UKESM1-1-LL</th>\n      <th>r1i1p1f2</th>\n      <th>gn</th>\n      <td>6</td>\n    </tr>\n  </tbody>\n</table>\n</div>","content_type":"text/html"}}}],"key":"tJwgflqfU1"}],"key":"RUhfNZ84Ny"},{"type":"block","kind":"notebook-content","children":[{"type":"heading","depth":2,"position":{"start":{"line":1,"column":1},"end":{"line":1,"column":1}},"children":[{"type":"text","value":"Summary","position":{"start":{"line":1,"column":1},"end":{"line":1,"column":1}},"key":"nDQfuPd36B"}],"identifier":"summary","label":"Summary","html_id":"summary","implicit":true,"key":"b6ePo5vEZS"},{"type":"paragraph","position":{"start":{"line":3,"column":1},"end":{"line":3,"column":1}},"children":[{"type":"text","value":"At this point, you would be ready to use ","position":{"start":{"line":3,"column":1},"end":{"line":3,"column":1}},"key":"lffGDXZF7M"},{"type":"inlineCode","value":"to_dataset_dict()","position":{"start":{"line":3,"column":1},"end":{"line":3,"column":1}},"key":"FjABDcAdZ0"},{"type":"text","value":" to download and load all datasets into a dictionary for analysis. The point of this notebook however is to expose the search capabilities. It is our goal to make annoying and time-consuming tasks easier by providing you smart interfaces for common operations. Let us ","position":{"start":{"line":3,"column":1},"end":{"line":3,"column":1}},"key":"eYpaoKKYRX"},{"type":"link","url":"https://github.com/esgf2-us/intake-esgf/issues","position":{"start":{"line":3,"column":1},"end":{"line":3,"column":1}},"children":[{"type":"text","value":"know","position":{"start":{"line":3,"column":1},"end":{"line":3,"column":1}},"key":"sFWVHZ1R8k"}],"urlSource":"https://github.com/esgf2-us/intake-esgf/issues","error":true,"key":"jdHpW1z5Jq"},{"type":"text","value":" what else is painful for you in locating relevant data for your science.","position":{"start":{"line":3,"column":1},"end":{"line":3,"column":1}},"key":"sqobW8N8Qq"}],"key":"HaOAcrkwkM"}],"key":"jV8WMIC7s0"}],"key":"Gq89EmSMoU"},"references":{"cite":{"order":["Gregory_2008"],"data":{"Gregory_2008":{"label":"Gregory_2008","enumerator":"1","doi":"10.1029/2008jd010405","html":"Gregory, J. M., & Forster, P. M. (2008). Transient climate response estimated from radiative forcing and observed temperature change. <i>Journal of Geophysical Research: Atmospheres</i>, <i>113</i>(D23). <a target=\"_blank\" rel=\"noreferrer\" href=\"https://doi.org/10.1029/2008jd010405\">10.1029/2008jd010405</a>","url":"https://doi.org/10.1029/2008jd010405"}}}},"footer":{"navigation":{"prev":{"title":"Introduction to intake-esgf","url":"/notebooks/intro-search","group":"Searching"},"next":{"title":"Compute Demo: Use Rooki to access CMIP6 data","url":"/notebooks/rooki","group":"Searching"}}},"domain":"http://localhost:3000"}